pysqlitehelper/__init__.py
pysqlitehelper/helpers.py
pysqlitehelper-0.4.0.dist-info/LICENSE
pysqlitehelper-0.4.0.dist-info/METADATA
pysqlitehelper-0.4.0.dist-info/WHEEL
pysqlitehelper-0.4.0.dist-info/RECORD
