Metadata-Version: 2.1
Name: pysqlitehelper
Version: 0.4.0
Summary: Python SQLiteHelper is a python package that help you to create sqlite databases,tables and interacting with sqlite database without have to worry about writing any SQL query.
License: MIT
Author: Fidele K
Author-email: itfidele@gmail.com
Requires-Python: >=3.9,<4.0
Classifier: License :: OSI Approved :: MIT License
Classifier: Programming Language :: Python :: 3
Classifier: Programming Language :: Python :: 3.9
Classifier: Programming Language :: Python :: 3.10
Classifier: Programming Language :: Python :: 3.11
Classifier: Programming Language :: Python :: 3.12
